{
  "main": {
    "id": "5c3fce855b79cd45",
    "type": "split",
    "children": [
      {
        "id": "a6735557aa3e8a29",
        "type": "tabs",
        "children": [
          {
            "id": "2e5d3b771e0d0866",
            "type": "leaf",
            "state": {
              "type": "markdown",
              "state": {
                "file": "package.json.md",
                "mode": "source",
                "source": false
              }
            }
          }
        ]
      }
    ],
    "direction": "vertical"
  },
  "left": {
    "id": "96fadb603ba00513",
    "type": "split",
    "children": [
      {
        "id": "d7b419805d72cdcc",
        "type": "tabs",
        "children": [
          {
            "id": "07af79ba6c1a80f2",
            "type": "leaf",
            "state": {
              "type": "file-explorer",
              "state": {
                "sortOrder": "alphabetical"
              }
            }
          },
          {
            "id": "f7aac954a08e082b",
            "type": "leaf",
            "state": {
              "type": "search",
              "state": {
                "query": "",
                "matchingCase": false,
                "explainSearch": false,
                "collapseAll": false,
                "extraContext": false,
                "sortOrder": "alphabetical"
              }
            }
          },
          {
            "id": "1c2775b8acef7106",
            "type": "leaf",
            "state": {
              "type": "bookmarks",
              "state": {}
            }
          }
        ]
      }
    ],
    "direction": "horizontal",
    "width": 300
  },
  "right": {
    "id": "e672f9257ef4b9d5",
    "type": "split",
    "children": [
      {
        "id": "6bfc5e43809cc457",
        "type": "tabs",
        "children": [
          {
            "id": "c0d8070fcbce1d65",
            "type": "leaf",
            "state": {
              "type": "backlink",
              "state": {
                "file": "package.json.md",
                "collapseAll": false,
                "extraContext": false,
                "sortOrder": "alphabetical",
                "showSearch": false,
                "searchQuery": "",
                "backlinkCollapsed": false,
                "unlinkedCollapsed": true
              }
            }
          },
          {
            "id": "67afba375988c125",
            "type": "leaf",
            "state": {
              "type": "outgoing-link",
              "state": {
                "file": "package.json.md",
                "linksCollapsed": false,
                "unlinkedCollapsed": true
              }
            }
          },
          {
            "id": "15bc4952ee6d4e03",
            "type": "leaf",
            "state": {
              "type": "tag",
              "state": {
                "sortOrder": "frequency",
                "useHierarchy": true
              }
            }
          },
          {
            "id": "6ccb9e790e365c84",
            "type": "leaf",
            "state": {
              "type": "outline",
              "state": {
                "file": "package.json.md"
              }
            }
          }
        ]
      }
    ],
    "direction": "horizontal",
    "width": 300
  },
  "left-ribbon": {
    "hiddenItems": {
      "switcher:打开快速切换": false,
      "graph:查看关系图谱": false,
      "canvas:新建白板": false,
      "daily-notes:打开/创建今天的日记": false,
      "templates:插入模板": false,
      "command-palette:打开命令面板": false
    }
  },
  "active": "2e5d3b771e0d0866",
  "lastOpenFiles": []
}